__init__.py
jupyter_lab_notebook_toc_utils.py
jupyter_lab_notebook_toc_utils-2024.5.13.1.dist-info/METADATA
jupyter_lab_notebook_toc_utils-2024.5.13.1.dist-info/WHEEL
jupyter_lab_notebook_toc_utils-2024.5.13.1.dist-info/top_level.txt
jupyter_lab_notebook_toc_utils-2024.5.13.1.dist-info/RECORD
