Metadata-Version: 2.1
Name: jupyter-lab-notebook-toc-utils
Version: 2024.5.13.1
Summary: Tools for creating a table of contents for a jupyter lab notebook.
Home-page: 
Author: tschneider
Author-email: tschneider@live.com
Classifier: Programming Language :: Unix Shell
Classifier: Programming Language :: Python :: 3
Classifier: License :: OSI Approved :: GNU Lesser General Public License v3 (LGPLv3)
Classifier: Operating System :: OS Independent
Requires-Dist: nbformat
Requires-Dist: nbconvert
Requires-Dist: IPython
Requires-Dist: ipynbname
